hdlConvertor_binary.libs/libantlr4-runtime-9df63605.so.4.8
hdlConvertor_binary-2.3.dist-info/WHEEL
hdlConvertor_binary-2.3.dist-info/top_level.txt
hdlConvertor_binary-2.3.dist-info/LICENSE
hdlConvertor_binary-2.3.dist-info/RECORD
hdlConvertor_binary-2.3.dist-info/METADATA
hdlConvertor/_hdlConvertor.cpython-39-x86_64-linux-gnu.so
hdlConvertor/__init__.py
