Metadata-Version: 2.1
Name: hdlConvertor-binary
Version: 2.3
Summary: VHDL and System Verilog parser written in c++
Home-page: https://github.com/Nic30/hdlConvertor
Author: Michal Orsak
Author-email: Nic30original@gmail.com
License: MIT
Keywords: hdl,vhdl,verilog,system verilog,parser,preprocessor,antlr4
Platform: UNKNOWN
Classifier: Development Status :: 4 - Beta
Classifier: Intended Audience :: Developers
Classifier: Intended Audience :: Science/Research
Classifier: Operating System :: OS Independent
Classifier: Topic :: Software Development :: Build Tools
Classifier: Programming Language :: C++
Classifier: Programming Language :: Cython
Classifier: Programming Language :: Python :: Implementation :: CPython
Classifier: Programming Language :: Python :: 2.7
Classifier: Programming Language :: Python :: 3
Classifier: Topic :: Scientific/Engineering :: Electronic Design Automation (EDA)
License-File: LICENSE
Requires-Dist: hdlConvertorAst >=1.0
